.gitignore
LICENSE
README.md
requirements.txt
requirements_extra.json
credsafe/__init__.py
credsafe/agent.py
credsafe/broker.py
credsafe/utils.py
credsafe-3.1.0.dist-info/LICENSE
credsafe-3.1.0.dist-info/METADATA
credsafe-3.1.0.dist-info/WHEEL
credsafe-3.1.0.dist-info/top_level.txt
credsafe-3.1.0.dist-info/RECORD
