Metadata-Version: 2.1
Name: credsafe
Version: 3.1.0
Summary: Store application credentials in keyring with RSA and AES-256.
Home-page: https://github.com/foxe6/
Author: f̣ộx̣ệ6
Author-email: foxe6@protonmail.com
License: AGPL-3.0
Project-URL: Sourcecode, https://github.com/foxe6/credsafe
Project-URL: Documentation, https://github.com/foxe6/credsafe/blob/master/test
Project-URL: Example, https://github.com/foxe6/credsafe/blob/master/credsafe/example
Project-URL: Issues, https://github.com/foxe6/credsafe/issues
Project-URL: Funding, https://paypal.me/foxe6
Project-URL: Say Thanks!, https://saythanks.io/to/foxe6
Keywords: credentials safe vault keyring rsa aes
Platform: UNKNOWN
Classifier: Programming Language :: Python :: 3.9
Classifier: Topic :: Utilities
Classifier: Natural Language :: English
Classifier: Intended Audience :: Developers
Classifier: License :: OSI Approved :: GNU Affero General Public License v3
Classifier: Operating System :: MacOS
Classifier: Operating System :: POSIX
Classifier: Operating System :: Microsoft :: Windows :: Windows 10
Classifier: Development Status :: 5 - Production/Stable
Requires-Python: >=3
License-File: LICENSE
Requires-Dist: aescipher (>=0.0.1)
Requires-Dist: easyrsa (>=0.0.1)
Requires-Dist: omnitools (>=0.0.1)
Requires-Dist: keyring (>=0.0.1)
